.appveyor.yml
.travis.yml
CHANGELOG.md
LICENSE.txt
README.md
amr.py
pyproject.toml
sample_file_list
setup.py
smatch-table.py
smatch.py
smatch_tool_guideline.txt
test_input1.txt
test_input2.txt
tox.ini
smatch.egg-info/PKG-INFO
smatch.egg-info/SOURCES.txt
smatch.egg-info/dependency_links.txt
smatch.egg-info/top_level.txt
tests/README.md
tests/test_top.py